sep_distances/__init__.py
sep_distances/metrics.py
sep_distances/mixed_graph.py
sep_distances/utils.py
sep_distances/tests/Graphs_for_testing.py
sep_distances/tests/__init__.py
sep_distances/tests/test_AIDs.py
sep_distances/tests/test_SD_CPDAGs.py
sep_distances/tests/test_SD_DAGs.py
sep_distances/tests/test_SD_mixed.py
sep_distances/tests/test_SHD.py
sep_distances/tests/test_ZL_separator_invariance.py
sep_distances/tests/test_c_metric_DAGs.py
sep_distances/tests/test_canonical_DAG.py
sep_distances/tests/test_causal_order.py
sep_distances/tests/test_find_minimal_separator_1.py
sep_distances/tests/test_get_CPDAG.py
sep_distances/tests/test_get_Markov_blanket.py
sep_distances/tests/test_get_acyclification.py
sep_distances/tests/test_get_ancestors.py
sep_distances/tests/test_get_possible_ancestors.py
sep_distances/tests/test_get_representative_of_MEC.py
sep_distances/tests/test_is_d_separated.py
sep_distances/tests/test_possibleparents_of.py
sep_distances/tests/test_s_metric_DAGs.py
sep_distances/tests/test_sc_metric_DAGs.py
sep_distances/tests/test_sc_metric_cyclic.py
sep_distances/tests/test_sc_metric_mixed_graphs.py
sep_distances/tests/test_answers/test_AIDs_answers.json
sep_distances/tests/test_answers/test_SD_CPDAGs_answers.json
sep_distances/tests/test_answers/test_SD_DAGs_answers.json
sep_distances/tests/test_answers/test_SD_mixed_answers.json
sep_distances/tests/test_answers/test_SHD_answers.json
sep_distances/tests/test_answers/test_c_metric_DAGs_answers.json
sep_distances/tests/test_answers/test_is_d_separated_answers.json
sep_distances/tests/test_answers/test_s_metric_DAGs_answers.json
sep_distances/tests/test_answers/test_sc_metric_DAGs_answers.json
sep_distances/tests/test_answers/test_sc_metric_cyclic_answers.json
sep_distances/tests/test_answers/test_sc_metric_mixed_graphs_answers.json
sep_distances-1.0.1.dist-info/LICENSE.txt
sep_distances-1.0.1.dist-info/METADATA
sep_distances-1.0.1.dist-info/WHEEL
sep_distances-1.0.1.dist-info/top_level.txt
sep_distances-1.0.1.dist-info/RECORD
