Metadata-Version: 2.2
Name: sep_distances
Version: 1.0.1
Summary: An implementation of separation distances and s/c-metrics for causal graphs as introduced in the paper 'Separation-based distance metrics for causal graphs'.
Home-page: https://github.com/JonasChoice/sep_distances
Author: Jonas Wahl
Author-email: jonas.wahl@dfki.de
License: GPL-3.0-only
Requires-Python: >=3.10
License-File: LICENSE.txt
Requires-Dist: gadjid>=0.1.0
Requires-Dist: networkx>=3.4.2
Requires-Dist: numpy>=2.2.3
Requires-Dist: scipy>=1.15.2
Requires-Dist: setuptools>=75.8.0
Requires-Dist: wheel>=0.45.1
Provides-Extra: dev
Requires-Dist: pytest>=7.0; extra == "dev"
Provides-Extra: twine
Requires-Dist: twine>=4.0.2; extra == "twine"
Dynamic: author
Dynamic: author-email
Dynamic: description
Dynamic: description-content-type
Dynamic: home-page
Dynamic: license
Dynamic: provides-extra
Dynamic: requires-dist
Dynamic: requires-python
Dynamic: summary
